logging_transport_json/__init__.py
logging_transport_json-0.1.dist-info/METADATA
logging_transport_json-0.1.dist-info/WHEEL
logging_transport_json-0.1.dist-info/top_level.txt
logging_transport_json-0.1.dist-info/RECORD
